ordeq_polars/__init__.py
ordeq_polars/_version.py
ordeq_polars/py.typed
ordeq_polars/eager/__init__.py
ordeq_polars/eager/csv.py
ordeq_polars/eager/excel.py
ordeq_polars/eager/iceberg.py
ordeq_polars/eager/json.py
ordeq_polars/eager/json_nd.py
ordeq_polars/eager/parquet.py
ordeq_polars/lazy/__init__.py
ordeq_polars/lazy/csv.py
ordeq_polars/lazy/iceberg.py
ordeq_polars/lazy/json_nd.py
ordeq_polars/lazy/parquet.py
ordeq_polars-1.1.2.dist-info/licenses/LICENSE
ordeq_polars-1.1.2.dist-info/METADATA
ordeq_polars-1.1.2.dist-info/WHEEL
ordeq_polars-1.1.2.dist-info/top_level.txt
ordeq_polars-1.1.2.dist-info/RECORD
