Metadata-Version: 2.4
Name: ordeq_polars
Version: 1.1.2
Summary: Polars integration for Ordeq
Author: Niels Neerhoff, Simon Brugman
Maintainer: Niels Neerhoff, Simon Brugman
License-Expression: MIT
Requires-Python: >=3.10
License-File: LICENSE
Requires-Dist: ordeq>=1.2.0
Requires-Dist: polars[pyarrow]>=1.0
Dynamic: license-file
